.npmnukeignore-template
LICENSE
MANIFEST.in
README.md
requirements.txt
setup.cfg
setup.py
npmnuke/__init__.py
npmnuke/app.py
npmnuke/cli.py
npmnuke/files.py
npmnuke/logger.py
npmnuke/main.py
npmnuke/models.py
npmnuke.egg-info/PKG-INFO
npmnuke.egg-info/SOURCES.txt
npmnuke.egg-info/dependency_links.txt
npmnuke.egg-info/entry_points.txt
npmnuke.egg-info/requires.txt
npmnuke.egg-info/top_level.txt
npmnuke/widgets/__init__.py
npmnuke/widgets/result_list.py
npmnuke/widgets/spinner.py
npmnuke/widgets/timer.py
test/__init__.py
test/test_files.py