Metadata-Version: 2.1
Name: npmnuke
Version: 0.2.1
Summary: Remove all node_modules folders from a directory
Author: cuire
Author-email: garwes@icloud.com
Requires-Python: >=3.10
License-File: LICENSE
